[
{
    "model": "auth.user",
    "pk": 1,
    "fields": {
        "password": "pbkdf2_sha256$720000$KRUeDfUMIgxTztyZqi2jX4$KRpPWSmEgEPTI9xUitp+hO3PzMB4708ArxaT+hp542E=",
        "last_login": "2024-06-16T17:09:02Z",
        "is_superuser": true,
        "username": "dyako",
        "first_name": "Артем",
        "last_name": "Дякович",
        "email": "dyakovich.artyom@yandex.ru",
        "is_staff": true,
        "is_active": true,
        "date_joined": "2024-06-16T17:05:53Z",
        "groups": [],
        "user_permissions": []
    }
},
{
    "model": "auth.user",
    "pk": 2,
    "fields": {
        "password": "pbkdf2_sha256$720000$HkIlDnPlbakk0wuFrsJdgN$Tey1Ahxt2hSCIVhbNgwGfswzXm76JP1q5oYV9Uuuruk=",
        "last_login": null,
        "is_superuser": false,
        "username": "gubkin.l",
        "first_name": "Леонид",
        "last_name": "Губкин",
        "email": "gubkin.l@star.ru",
        "is_staff": true,
        "is_active": true,
        "date_joined": "2024-06-16T22:05:23Z",
        "groups": [
            2
        ],
        "user_permissions": [
            1,
            2,
            3,
            4,
            9,
            10,
            11,
            12,
            5,
            6,
            7,
            8,
            13,
            14,
            15,
            16,
            17,
            18,
            19,
            20,
            49,
            50,
            51,
            52,
            45,
            46,
            47,
            48,
            29,
            30,
            31,
            32,
            37,
            38,
            39,
            40,
            25,
            26,
            27,
            28,
            41,
            42,
            43,
            44,
            33,
            34,
            35,
            36,
            21,
            22,
            23,
            24
        ]
    }
},
{
    "model": "auth.user",
    "pk": 3,
    "fields": {
        "password": "pbkdf2_sha256$720000$5kNJ5N1Ltxe3IkOrLftSmc$kf5kQMNjVJh7fcRPETMtvd7uqgXbhJUcWD85DISHP78=",
        "last_login": null,
        "is_superuser": false,
        "username": "korotkov.s",
        "first_name": "Сергей",
        "last_name": "Коротков",
        "email": "korotkov.s@star.ru",
        "is_staff": true,
        "is_active": true,
        "date_joined": "2024-06-16T22:05:55Z",
        "groups": [
            2
        ],
        "user_permissions": [
            1,
            2,
            3,
            4,
            9,
            10,
            11,
            12,
            5,
            6,
            7,
            8,
            13,
            14,
            15,
            16,
            17,
            18,
            19,
            20,
            49,
            50,
            51,
            52,
            45,
            46,
            47,
            48,
            29,
            30,
            31,
            32,
            37,
            38,
            39,
            40,
            25,
            26,
            27,
            28,
            41,
            42,
            43,
            44,
            33,
            34,
            35,
            36,
            21,
            22,
            23,
            24
        ]
    }
},
{
    "model": "auth.user",
    "pk": 4,
    "fields": {
        "password": "pbkdf2_sha256$720000$6FCH160xGeIeP2SORfbjZr$n5IVxxTpcBYrd5nS7+z6Va2uCGG9lRqrkarocJNR9Hw=",
        "last_login": null,
        "is_superuser": false,
        "username": "cherkesov.v",
        "first_name": "Виктор",
        "last_name": "Черкесов",
        "email": "cherkesov.v@star.ru",
        "is_staff": true,
        "is_active": true,
        "date_joined": "2024-06-16T22:06:37Z",
        "groups": [
            2
        ],
        "user_permissions": [
            1,
            2,
            3,
            4,
            9,
            10,
            11,
            12,
            5,
            6,
            7,
            8,
            13,
            14,
            15,
            16,
            17,
            18,
            19,
            20,
            49,
            50,
            51,
            52,
            45,
            46,
            47,
            48,
            29,
            30,
            31,
            32,
            37,
            38,
            39,
            40,
            25,
            26,
            27,
            28,
            41,
            42,
            43,
            44,
            33,
            34,
            35,
            36,
            21,
            22,
            23,
            24
        ]
    }
},
{
    "model": "auth.user",
    "pk": 5,
    "fields": {
        "password": "pbkdf2_sha256$720000$c9kAo7lqJaRfdu9CO0dBxH$6YGf5Rg31fOt091Xz7bbdrvSgqmuHa9Evwej97fC+Uw=",
        "last_login": null,
        "is_superuser": false,
        "username": "yakovlev.d",
        "first_name": "Дмитрий",
        "last_name": "Яковлев",
        "email": "yakovlev.d@star.ru",
        "is_staff": true,
        "is_active": true,
        "date_joined": "2024-06-16T22:06:52Z",
        "groups": [
            2
        ],
        "user_permissions": [
            1,
            2,
            3,
            4,
            9,
            10,
            11,
            12,
            5,
            6,
            7,
            8,
            13,
            14,
            15,
            16,
            17,
            18,
            19,
            20,
            49,
            50,
            51,
            52,
            45,
            46,
            47,
            48,
            29,
            30,
            31,
            32,
            37,
            38,
            39,
            40,
            25,
            26,
            27,
            28,
            41,
            42,
            43,
            44,
            33,
            34,
            35,
            36,
            21,
            22,
            23,
            24
        ]
    }
},
{
    "model": "auth.user",
    "pk": 6,
    "fields": {
        "password": "pbkdf2_sha256$720000$8GTJ4ACGhy4i6HWYH2zYWY$s0KDfdOIOR4hybGaAjYYNlYSdKJGigJKDhdsLmWDidw=",
        "last_login": null,
        "is_superuser": false,
        "username": "kryatalov.s",
        "first_name": "Сергей",
        "last_name": "Кряталов",
        "email": "kryatalov.s@star.ru",
        "is_staff": true,
        "is_active": true,
        "date_joined": "2024-06-16T22:07:10Z",
        "groups": [
            2
        ],
        "user_permissions": [
            1,
            2,
            3,
            4,
            9,
            10,
            11,
            12,
            5,
            6,
            7,
            8,
            13,
            14,
            15,
            16,
            17,
            18,
            19,
            20,
            49,
            50,
            51,
            52,
            45,
            46,
            47,
            48,
            29,
            30,
            31,
            32,
            37,
            38,
            39,
            40,
            25,
            26,
            27,
            28,
            41,
            42,
            43,
            44,
            33,
            34,
            35,
            36,
            21,
            22,
            23,
            24
        ]
    }
},
{
    "model": "auth.user",
    "pk": 7,
    "fields": {
        "password": "pbkdf2_sha256$720000$AsYcQTPkQ9SEA16DNxmaP4$jL5dC2fuat2AthBst0jF9mxJ1c9Fi03tA3LIpPtd0ic=",
        "last_login": null,
        "is_superuser": false,
        "username": "ivanov.d",
        "first_name": "Дмитрий",
        "last_name": "Иванов",
        "email": "ivanov.d@star.ru",
        "is_staff": false,
        "is_active": true,
        "date_joined": "2024-06-16T22:10:20Z",
        "groups": [
            3
        ],
        "user_permissions": []
    }
},
{
    "model": "auth.user",
    "pk": 8,
    "fields": {
        "password": "pbkdf2_sha256$720000$DIKHJMNJzyMK8SN7ITFQbX$4CpACscCNgJTqQokVlk19UG1ZtaghpQg7T9vz7EW694=",
        "last_login": null,
        "is_superuser": false,
        "username": "slepakov.n",
        "first_name": "Николай",
        "last_name": "Слепаков",
        "email": "slepakov.n@star.ru",
        "is_staff": false,
        "is_active": true,
        "date_joined": "2024-06-16T22:11:30Z",
        "groups": [
            3
        ],
        "user_permissions": []
    }
},
{
    "model": "auth.user",
    "pk": 9,
    "fields": {
        "password": "pbkdf2_sha256$720000$oOdmzHBMIsvDiARCxTdvVf$IWzTf3WTN6WGW6xhZnWjaD2dNemrOa2h6sosXZ8F3Co=",
        "last_login": null,
        "is_superuser": false,
        "username": "petrov.p",
        "first_name": "Павел",
        "last_name": "Петров",
        "email": "petrov.p@star.ru",
        "is_staff": false,
        "is_active": true,
        "date_joined": "2024-06-16T22:12:23Z",
        "groups": [
            4
        ],
        "user_permissions": []
    }
},
{
    "model": "auth.user",
    "pk": 10,
    "fields": {
        "password": "pbkdf2_sha256$720000$b3FETybluVs92cOI5w30KI$6RXyPKRQYyj9OzGpNwTQPmd2Q0OXqzxzsFgbKON3FIw=",
        "last_login": null,
        "is_superuser": false,
        "username": "smirnov.a",
        "first_name": "Алексей",
        "last_name": "Смирнов",
        "email": "smirnov.a@star.ru",
        "is_staff": false,
        "is_active": true,
        "date_joined": "2024-06-16T22:14:31Z",
        "groups": [
            4
        ],
        "user_permissions": []
    }
},
{
    "model": "auth.user",
    "pk": 11,
    "fields": {
        "password": "pbkdf2_sha256$720000$R8NHqXS1oK5FdDHZFEpOAV$chtpxc8vLLotAAto4shQFC9wSfqo5Ir6oMbfqbALQtY=",
        "last_login": null,
        "is_superuser": false,
        "username": "kuznetsov.m",
        "first_name": "Максим",
        "last_name": "Кузнецов",
        "email": "kuznetsov.m@star.ru",
        "is_staff": false,
        "is_active": true,
        "date_joined": "2024-06-16T22:14:53Z",
        "groups": [
            5
        ],
        "user_permissions": []
    }
},
{
    "model": "auth.user",
    "pk": 12,
    "fields": {
        "password": "pbkdf2_sha256$720000$YtIWVGa7PuyvOyVlYJUFKB$j5piIpUf65ymjuaZ1jTEwHEGjFjcYmtoEQSBaRsdsSM=",
        "last_login": null,
        "is_superuser": false,
        "username": "popov.s",
        "first_name": "Семен",
        "last_name": "Попов",
        "email": "popov.s@star.ru",
        "is_staff": false,
        "is_active": true,
        "date_joined": "2024-06-16T22:15:13Z",
        "groups": [
            5
        ],
        "user_permissions": []
    }
},
{
    "model": "auth.user",
    "pk": 13,
    "fields": {
        "password": "pbkdf2_sha256$720000$IUHqvWoeS4B2mhDkZDW5B2$P0EUNLvjdLOOHzZvh+teaAVhPC0zSKM05izv9FfriRE=",
        "last_login": null,
        "is_superuser": false,
        "username": "vasilyev.n",
        "first_name": "Николай",
        "last_name": "Васильев",
        "email": "vasilyev.n@star.ru",
        "is_staff": false,
        "is_active": true,
        "date_joined": "2024-06-16T22:15:48Z",
        "groups": [
            6
        ],
        "user_permissions": []
    }
},
{
    "model": "auth.user",
    "pk": 14,
    "fields": {
        "password": "pbkdf2_sha256$720000$P8ObFpM3m87eiz2yRjd9LF$ohyuNG5pruh5QtN5sbKIDjv463SrCBRelPfNkD+NhdY=",
        "last_login": null,
        "is_superuser": false,
        "username": "morozov.y",
        "first_name": "Илья",
        "last_name": "Морозов",
        "email": "morozov.y@star.ru",
        "is_staff": false,
        "is_active": true,
        "date_joined": "2024-06-16T22:16:11Z",
        "groups": [
            6
        ],
        "user_permissions": []
    }
},
{
    "model": "main.userprofile",
    "pk": 1,
    "fields": {
        "user": 2,
        "patronymic": "Александрович",
        "phone_number": "+79995552555",
        "job_title": "Начальник отдела"
    }
},
{
    "model": "main.userprofile",
    "pk": 2,
    "fields": {
        "user": 3,
        "patronymic": "Владимирович",
        "phone_number": "+79995552555",
        "job_title": "Заместитель начальника"
    }
},
{
    "model": "main.userprofile",
    "pk": 3,
    "fields": {
        "user": 4,
        "patronymic": "Алексеевич",
        "phone_number": "89995552555",
        "job_title": "Заместитель начальника"
    }
},
{
    "model": "main.userprofile",
    "pk": 4,
    "fields": {
        "user": 5,
        "patronymic": "Владимирович",
        "phone_number": "+79995552555",
        "job_title": "Начальник бюро по работе с руководителями и специалистами"
    }
},
{
    "model": "main.userprofile",
    "pk": 5,
    "fields": {
        "user": 6,
        "patronymic": "Владимирович",
        "phone_number": "+79995552555",
        "job_title": "Секретарь ОК"
    }
},
{
    "model": "main.userprofile",
    "pk": 6,
    "fields": {
        "user": 7,
        "patronymic": "Владимирович",
        "phone_number": "+79995552555",
        "job_title": "Помощник"
    }
},
{
    "model": "main.userprofile",
    "pk": 7,
    "fields": {
        "user": 8,
        "patronymic": "Алексеевич",
        "phone_number": "+79995552555",
        "job_title": "Помощник"
    }
},
{
    "model": "main.userprofile",
    "pk": 8,
    "fields": {
        "user": 9,
        "patronymic": "Александрович",
        "phone_number": "+79995552555",
        "job_title": "Помощник"
    }
},
{
    "model": "main.userprofile",
    "pk": 9,
    "fields": {
        "user": 11,
        "patronymic": "Владимирович",
        "phone_number": "+79995552555",
        "job_title": "Помощник"
    }
},
{
    "model": "main.userprofile",
    "pk": 10,
    "fields": {
        "user": 12,
        "patronymic": "Александрович",
        "phone_number": "+79995552555",
        "job_title": "Помощник"
    }
},
{
    "model": "main.userprofile",
    "pk": 11,
    "fields": {
        "user": 10,
        "patronymic": "Александрович",
        "phone_number": "+79995552555",
        "job_title": "Помощник"
    }
},
{
    "model": "main.userprofile",
    "pk": 12,
    "fields": {
        "user": 14,
        "patronymic": "Владимирович",
        "phone_number": "+79995552555",
        "job_title": "Помощник"
    }
},
{
    "model": "main.userprofile",
    "pk": 13,
    "fields": {
        "user": 13,
        "patronymic": "Александрович",
        "phone_number": "+79995552555",
        "job_title": "Помощник"
    }
},
{
    "model": "main.userprofile",
    "pk": 14,
    "fields": {
        "user": 1,
        "patronymic": "Александрович",
        "phone_number": "+79581671352",
        "job_title": "Админ"
    }
}
]
